LICENSE
README.md
setup.cfg
setup.py
authz_sdk/__init__.py
authz_sdk/api_pb2.py
authz_sdk/api_pb2_grpc.py
authz_sdk/client.py
authz_sdk.egg-info/PKG-INFO
authz_sdk.egg-info/SOURCES.txt
authz_sdk.egg-info/dependency_links.txt
authz_sdk.egg-info/requires.txt
authz_sdk.egg-info/top_level.txt
authz_sdk/interceptor/__init__.py
authz_sdk/interceptor/client_authentication.py